cirq/__init__.py
cirq/_compat.py
cirq/_compat_test.py
cirq/_doc.py
cirq/_import.py
cirq/_import_test.py
cirq/_version.py
cirq/_version_test.py
cirq/conftest.py
cirq/json_resolver_cache.py
cirq/py.typed
cirq/circuits/__init__.py
cirq/circuits/_block_diagram_drawer.py
cirq/circuits/_block_diagram_drawer_test.py
cirq/circuits/_box_drawing_character_data.py
cirq/circuits/_box_drawing_character_data_test.py
cirq/circuits/_bucket_priority_queue.py
cirq/circuits/_bucket_priority_queue_test.py
cirq/circuits/circuit.py
cirq/circuits/circuit_operation.py
cirq/circuits/circuit_operation_test.py
cirq/circuits/circuit_test.py
cirq/circuits/frozen_circuit.py
cirq/circuits/frozen_circuit_test.py
cirq/circuits/insert_strategy.py
cirq/circuits/insert_strategy_test.py
cirq/circuits/moment.py
cirq/circuits/moment_test.py
cirq/circuits/optimization_pass.py
cirq/circuits/optimization_pass_test.py
cirq/circuits/qasm_output.py
cirq/circuits/qasm_output_test.py
cirq/circuits/text_diagram_drawer.py
cirq/circuits/text_diagram_drawer_test.py
cirq/contrib/__init__.py
cirq/contrib/json.py
cirq/contrib/json_test.py
cirq/contrib/acquaintance/__init__.py
cirq/contrib/acquaintance/bipartite.py
cirq/contrib/acquaintance/bipartite_test.py
cirq/contrib/acquaintance/devices.py
cirq/contrib/acquaintance/devices_test.py
cirq/contrib/acquaintance/executor.py
cirq/contrib/acquaintance/executor_test.py
cirq/contrib/acquaintance/gates.py
cirq/contrib/acquaintance/gates_test.py
cirq/contrib/acquaintance/inspection_utils.py
cirq/contrib/acquaintance/inspection_utils_test.py
cirq/contrib/acquaintance/mutation_utils.py
cirq/contrib/acquaintance/mutation_utils_test.py
cirq/contrib/acquaintance/optimizers.py
cirq/contrib/acquaintance/optimizers_test.py
cirq/contrib/acquaintance/permutation.py
cirq/contrib/acquaintance/permutation_test.py
cirq/contrib/acquaintance/shift.py
cirq/contrib/acquaintance/shift_swap_network.py
cirq/contrib/acquaintance/shift_swap_network_test.py
cirq/contrib/acquaintance/shift_test.py
cirq_core-1.6.0.dist-info/licenses/LICENSE
cirq_core-1.6.0.dist-info/METADATA
cirq_core-1.6.0.dist-info/WHEEL
cirq_core-1.6.0.dist-info/top_level.txt
cirq_core-1.6.0.dist-info/RECORD
