Metadata-Version: 2.4
Name: cirq-core
Version: 1.6.0
Summary: A framework for creating, editing, and invoking Noisy Intermediate Scale Quantum (NISQ) circuits.
Home-page: http://github.com/quantumlib/cirq
Author: The Cirq Developers
Author-email: cirq-dev@googlegroups.com
Maintainer: The Quantum AI open-source software maintainers
Maintainer-email: quantum-oss-maintainers@google.com
License: Apache 2
Keywords: algorithms,api,cirq,google,google quantum,nisq,python,quantum,quantum algorithms,quantum circuit,quantum circuit simulator,quantum computer simulator,quantum computing,quantum development kit,quantum information,quantum programming,quantum programming language,quantum simulation,sdk,simulation
Classifier: Development Status :: 5 - Production/Stable
Classifier: Intended Audience :: Developers
Classifier: Intended Audience :: Education
Classifier: Intended Audience :: Science/Research
Classifier: License :: OSI Approved :: Apache Software License
Classifier: Operating System :: MacOS :: MacOS X
Classifier: Operating System :: Microsoft :: Windows
Classifier: Operating System :: POSIX :: Linux
Classifier: Programming Language :: Python :: 3
Classifier: Programming Language :: Python :: 3.11
Classifier: Programming Language :: Python :: 3.12
Classifier: Programming Language :: Python :: 3.13
Classifier: Topic :: Scientific/Engineering :: Quantum Computing
Classifier: Topic :: Software Development :: Libraries :: Python Modules
Classifier: Typing :: Typed
Requires-Python: >=3.11.0
License-File: LICENSE
Requires-Dist: attrs>=21.3.0
Requires-Dist: duet>=0.2.8
Requires-Dist: matplotlib~=3.8
Requires-Dist: networkx~=3.4
Requires-Dist: numpy>=1.26
Requires-Dist: pandas~=2.1
Requires-Dist: sortedcontainers~=2.0
Requires-Dist: scipy~=1.12
Requires-Dist: sympy
Requires-Dist: typing_extensions>=4.2
Requires-Dist: tqdm>=4.12
Provides-Extra: contrib
Requires-Dist: ply>=3.6; extra == "contrib"
Requires-Dist: pylatex~=1.4; extra == "contrib"
Requires-Dist: quimb>=1.8; extra == "contrib"
Requires-Dist: opt_einsum; extra == "contrib"
Dynamic: author
Dynamic: author-email
Dynamic: classifier
Dynamic: description
Dynamic: description-content-type
Dynamic: home-page
Dynamic: keywords
Dynamic: license
Dynamic: license-file
Dynamic: maintainer
Dynamic: maintainer-email
Dynamic: provides-extra
Dynamic: requires-dist
Dynamic: requires-python
Dynamic: summary
